[{"date":null,"dateposted":null,"description":null,"id":null,"title":null,"uri":"/projects/arpg/index.json"},{"date":null,"dateposted":null,"description":null,"id":null,"title":null,"uri":"/projects/busy-richard/index.json"},{"date":null,"dateposted":null,"description":null,"id":null,"title":null,"uri":"/projects/dots/index.json"},{"date":null,"dateposted":null,"description":null,"id":null,"title":null,"uri":"/projects/paladin/index.json"},{"date":null,"dateposted":null,"description":null,"id":null,"title":null,"uri":"/projects/searcher/index.json"},{"date":null,"dateposted":null,"description":null,"id":null,"title":null,"uri":"/projects/vfx/index.json"}]